<?xml version="1.0" encoding="utf-8"?>
<TextureAtlas imagePath="finalformcrisbobal1.png">
	<!-- Created with Adobe Animate version 20.0.0.17400 -->
	<!-- http://www.adobe.com/products/animate.html -->
	<SubTexture name="bobdown0000" x="10" y="10" width="1199" height="1243"/>
	<SubTexture name="bobdown0001" x="10" y="10" width="1199" height="1243"/>
	<SubTexture name="bobdown0002" x="10" y="10" width="1199" height="1243"/>
	<SubTexture name="bobdown0003" x="1219" y="10" width="1199" height="1243"/>
	<SubTexture name="bobdown0004" x="1219" y="10" width="1199" height="1243"/>
	<SubTexture name="bobdown0005" x="1219" y="10" width="1199" height="1243"/>
	<SubTexture name="bobdown0006" x="1219" y="10" width="1199" height="1243"/>
	<SubTexture name="bobdown0007" x="1219" y="10" width="1199" height="1243"/>
	<SubTexture name="bobdown0008" x="1219" y="10" width="1199" height="1243"/>
	<SubTexture name="bobdown0009" x="1219" y="10" width="1199" height="1243"/>
	<SubTexture name="bobdown0010" x="1219" y="10" width="1199" height="1243"/>
	<SubTexture name="bobdown0011" x="1219" y="10" width="1199" height="1243"/>
	<SubTexture name="bobdown0012" x="1219" y="10" width="1199" height="1243"/>
	<SubTexture name="bobdown0013" x="1219" y="10" width="1199" height="1243"/>
	<SubTexture name="bobdown0014" x="1219" y="10" width="1199" height="1243"/>
	<SubTexture name="bobidle0000" x="2428" y="10" width="1199" height="1243"/>
	<SubTexture name="bobidle0001" x="2428" y="10" width="1199" height="1243"/>
	<SubTexture name="bobidle0002" x="2428" y="10" width="1199" height="1243"/>
	<SubTexture name="bobidle0003" x="3637" y="10" width="1199" height="1243"/>
	<SubTexture name="bobidle0004" x="3637" y="10" width="1199" height="1243"/>
	<SubTexture name="bobidle0005" x="3637" y="10" width="1199" height="1243"/>
	<SubTexture name="bobleft0000" x="4846" y="10" width="1199" height="1243"/>
	<SubTexture name="bobleft0001" x="4846" y="10" width="1199" height="1243"/>
	<SubTexture name="bobleft0002" x="4846" y="10" width="1199" height="1243"/>
	<SubTexture name="bobleft0003" x="6055" y="10" width="1199" height="1243"/>
	<SubTexture name="bobleft0004" x="6055" y="10" width="1199" height="1243"/>
	<SubTexture name="bobleft0005" x="6055" y="10" width="1199" height="1243"/>
	<SubTexture name="bobleft0006" x="6055" y="10" width="1199" height="1243"/>
	<SubTexture name="bobleft0007" x="6055" y="10" width="1199" height="1243"/>
	<SubTexture name="bobleft0008" x="6055" y="10" width="1199" height="1243"/>
	<SubTexture name="bobleft0009" x="6055" y="10" width="1199" height="1243"/>
	<SubTexture name="bobleft0010" x="6055" y="10" width="1199" height="1243"/>
	<SubTexture name="bobleft0011" x="6055" y="10" width="1199" height="1243"/>
	<SubTexture name="bobleft0012" x="6055" y="10" width="1199" height="1243"/>
	<SubTexture name="bobleft0013" x="6055" y="10" width="1199" height="1243"/>
	<SubTexture name="bobleft0014" x="6055" y="10" width="1199" height="1243"/>
	<SubTexture name="bobright0000" x="10" y="1263" width="1199" height="1243"/>
	<SubTexture name="bobright0001" x="10" y="1263" width="1199" height="1243"/>
	<SubTexture name="bobright0002" x="10" y="1263" width="1199" height="1243"/>
	<SubTexture name="bobright0003" x="1219" y="1263" width="1199" height="1243"/>
	<SubTexture name="bobright0004" x="1219" y="1263" width="1199" height="1243"/>
	<SubTexture name="bobright0005" x="1219" y="1263" width="1199" height="1243"/>
	<SubTexture name="bobright0006" x="1219" y="1263" width="1199" height="1243"/>
	<SubTexture name="bobright0007" x="1219" y="1263" width="1199" height="1243"/>
	<SubTexture name="bobright0008" x="1219" y="1263" width="1199" height="1243"/>
	<SubTexture name="bobright0009" x="1219" y="1263" width="1199" height="1243"/>
	<SubTexture name="bobright0010" x="1219" y="1263" width="1199" height="1243"/>
	<SubTexture name="bobright0011" x="1219" y="1263" width="1199" height="1243"/>
	<SubTexture name="bobright0012" x="1219" y="1263" width="1199" height="1243"/>
	<SubTexture name="bobright0013" x="1219" y="1263" width="1199" height="1243"/>
	<SubTexture name="bobright0014" x="1219" y="1263" width="1199" height="1243"/>
	<SubTexture name="bobup0000" x="2428" y="1263" width="1199" height="1243"/>
	<SubTexture name="bobup0001" x="2428" y="1263" width="1199" height="1243"/>
	<SubTexture name="bobup0002" x="2428" y="1263" width="1199" height="1243"/>
	<SubTexture name="bobup0003" x="3637" y="1263" width="1199" height="1243"/>
	<SubTexture name="bobup0004" x="3637" y="1263" width="1199" height="1243"/>
	<SubTexture name="bobup0005" x="3637" y="1263" width="1199" height="1243"/>
	<SubTexture name="bobup0006" x="3637" y="1263" width="1199" height="1243"/>
	<SubTexture name="bobup0007" x="3637" y="1263" width="1199" height="1243"/>
	<SubTexture name="bobup0008" x="3637" y="1263" width="1199" height="1243"/>
	<SubTexture name="bobup0009" x="3637" y="1263" width="1199" height="1243"/>
	<SubTexture name="bobup0010" x="3637" y="1263" width="1199" height="1243"/>
	<SubTexture name="bobup0011" x="3637" y="1263" width="1199" height="1243"/>
</TextureAtlas>
